paneltime/__init__.py
paneltime/debug.py
paneltime/functions.py
paneltime/info.py
paneltime/main.py
paneltime/options.py
paneltime/random_effects.py
paneltime/cfunctions/__init__.py
paneltime/cfunctions/ctypes.cpp
paneltime/cfunctions/ctypes.dll
paneltime/cfunctions/ctypes.dylib
paneltime/cfunctions/ctypes.exp
paneltime/cfunctions/ctypes.lib
paneltime/cfunctions/ctypes.obj
paneltime/cfunctions/ctypes.so
paneltime/cfunctions/exprtk.hpp
paneltime/cfunctions/mathexp.cpp
paneltime/likelihood/__init__.py
paneltime/likelihood/arma.py
paneltime/likelihood/calculus.py
paneltime/likelihood/calculus_functions.py
paneltime/likelihood/function.py
paneltime/likelihood/hfunc.py
paneltime/likelihood/main.py
paneltime/likelihood/models.py
paneltime/maximization/__init__.py
paneltime/maximization/computation.py
paneltime/maximization/constraints.py
paneltime/maximization/dfpmax.py
paneltime/maximization/direction.py
paneltime/maximization/init.py
paneltime/maximization/linesearch.py
paneltime/maximization/maximize.py
paneltime/output/__init__.py
paneltime/output/charts.py
paneltime/output/communication.py
paneltime/output/latex.py
paneltime/output/output.py
paneltime/output/stat_dist.py
paneltime/output/stat_functions.py
paneltime/processing/__init__.py
paneltime/processing/arguments.py
paneltime/processing/conversion.py
paneltime/processing/initreg.py
paneltime/processing/loaddata.py
paneltime/processing/model_parser.py
paneltime/processing/panel.py
paneltime-1.2.69.dist-info/licenses/LICENSE
qmd/example.py
qmd/loadwb.py
qmd/mymodel.py
paneltime-1.2.69.dist-info/METADATA
paneltime-1.2.69.dist-info/WHEEL
paneltime-1.2.69.dist-info/entry_points.txt
paneltime-1.2.69.dist-info/top_level.txt
paneltime-1.2.69.dist-info/RECORD
