Metadata-Version: 2.4
Name: paneltime
Version: 1.2.69
Summary: Panel regression simultaneously solving for ARIMA/GARCH and random/fixed effects.
Author-email: Espen Sirnes <espen.sirnes@uit.no>
License-Expression: GPL-3.0-only
Project-URL: Homepage, https://github.com/espensirnes/paneltime
Keywords: econometrics
Classifier: Development Status :: 4 - Beta
Classifier: Intended Audience :: Science/Research
Classifier: Topic :: Scientific/Engineering
Classifier: Programming Language :: Python :: 3.8
Requires-Python: >=3.8
License-File: LICENSE
Requires-Dist: numpy>=1.11
Requires-Dist: pandas>=1.0
Requires-Dist: mpmath>=1.1
Provides-Extra: linux
Requires-Dist: gcc; extra == "linux"
Dynamic: license-file
